[
    {
        "img": "https://image.wanted.co.kr/optimize?src=https%3A%2F%2Fwanted.video.kr.kollus.com%2Fkr%2Fsnapshot%2Fwanted%2F20210809%2F1%2F04517561.jpg&w=750&q=100",
        "tag": ["데이터", "IT/기술"],
        "title": "태블로로 대시보드 만들기 1",
        "detail": "회사에서 데이터를 볼 때 어떤 도구를 사용하시나요? 이번 영상에서는 태블로로 대시보드 만들기 기초를 소개합니다. 태블로의 기본 기능을 알아보고 대시보드를 만들기 위해 필요한 기본기를 익힙니다. DB에서 데이터를 연결하고, 원하는 형태로 데이터를 출력하며, 만든 대시보드를 공유하는 방법에 대해 알아봅니다.",
        "writer": "라인플러스 고종범",
        "profile": "https://image.wanted.co.kr/optimize?src=https%3A%2F%2Fstatic.wanted.co.kr%2Ffavicon%2F144x144.png&w=60&q=90"
    },
    {
        "img": "https://image.wanted.co.kr/optimize?src=https%3A%2F%2Fstatic.wanted.co.kr%2Fimages%2Fevents%2F2420%2F0423f3e8.jpg&w=1200&q=90",
        "tag": ["개발", "IT/기술", "취업/이직"],
        "title": "리걸테크 시장에 혁신을 더할 마크비전 엔지니어링팀",
        "detail": "Support Engineering 팀 Cloud Support Engineer(CSE)와 Cloud Support Associate(CSA)로서의 커리어와 일하는 문화를 궁금해 하시는 분이 많은데요. 보현 님과 오늘 인터뷰를 통해 궁금증을 풀어나가 보시길 바랍니다.",
        "writer": "플라브 코퍼레이션, 박상욱",
        "profile": "https://image.wanted.co.kr/optimize?src=https%3A%2F%2Fstatic.wanted.co.kr%2Ffavicon%2F144x144.png&w=60&q=90"
    },
    {
        "img": "https://image.wanted.co.kr/optimize?src=https%3A%2F%2Fstatic.wanted.co.kr%2Fimages%2Fevents%2F1786%2F81ade178.jpg&w=1200&q=90",
        "tag": ["개발", "취업/이직", "IT/기술"],
        "title": "신입 개발자, 뭘 공부애햐 하죠",
        "detail": "우리는 꼭 엄청나게 훌륭한 개발자가 되어야만 하나요? 계속해서 성장하는 개발자여야만 하나요? 그렇지 않습니다. 물론 성장하는 것 자체는 좋은 일이겠지만, 그러기 위해 한순간도 쉬지 않고 끊임없이 달리기만 해야 하는 건 아니에요. 힘들 때는 그냥 쉬어 가세요. 그게 개발자로 오래오래 일할 수 있는 더 좋은 방법이라고 생각해요. 10년쯤 일하다 보면 다 비슷해져요. 그러니까 압박을 심하게 받지 않으셨으면 해요. 공부하는 건 좋죠. 그런데 남들이 '개발자는 끊임없이 성장해야 한다'고들 하니까 그 말에 쫓기듯이 공부만 하는건 여러분 인생에 그닥 바람직하지 않다고 생각해요. 본인 상황에 맞는 페이스를 찾아서 공부와 휴식, 여가 등을 적절히 분배하시길 바랍니다.",
        "writer": "플라브 코퍼레이션, 박상욱",
        "profile": "https://image.wanted.co.kr/optimize?src=https%3A%2F%2Fstatic.wanted.co.kr%2Ffavicon%2F144x144.png&w=60&q=90"
    },
    {
        "img": "https://image.wanted.co.kr/optimize?src=https%3A%2F%2Fstatic.wanted.co.kr%2Fimages%2Fevents%2F2528%2Fbddb34c9.jpg&w=1200&q=90",
        "tag": ["개발", "취업/이직", "IT/기술"],
        "title": "개발자 면접 완전 정복하기 (1) - 코딩테스트 편",
        "detail": "개발자 면접은 길고 어렵습니다. 하지만 그렇다고 지레 겁먹을 필요는 없어요. 준비만 잘하면 누구나 좋은 결과를 볼 수 있습니다. 처음 이직 시도를 했을 때 면접에서 장렬히 전사했던 제가 얼마 전 세 번째 이직에 성공한 것이 그 증거입니다. ‘지피지기면 백전불태’라는 말처럼, 적을 알고 나를 알면 백번 싸워도 위태롭지 않습니다. 여기서 우리의 적은 면접입니다. 위태롭지 않게 면접에서 승리하기 위해서 우리는 준비해야 합니다. 앞으로의 글을 따라 함께 준비해 보아요!",
        "writer": "플라브 코퍼레이션, 박상욱",
        "profile": "https://image.wanted.co.kr/optimize?src=https%3A%2F%2Fstatic.wanted.co.kr%2Ffavicon%2F144x144.png&w=60&q=90"
    },
    {
        "img": "https://image.wanted.co.kr/optimize?src=https%3A%2F%2Fwanted.video.kr.kollus.com%2Fkr%2Fsnapshot%2Fwanted%2F20210809%2F1%2F04517561.jpg&w=750&q=100",
        "tag": ["데이터", "IT/기술"],
        "title": "태블로로 대시보드 만들기 1",
        "detail": "회사에서 데이터를 볼 때 어떤 도구를 사용하시나요? 이번 영상에서는 태블로로 대시보드 만들기 기초를 소개합니다. 태블로의 기본 기능을 알아보고 대시보드를 만들기 위해 필요한 기본기를 익힙니다. DB에서 데이터를 연결하고, 원하는 형태로 데이터를 출력하며, 만든 대시보드를 공유하는 방법에 대해 알아봅니다.",
        "writer": "라인플러스 고종범",
        "profile": "https://image.wanted.co.kr/optimize?src=https%3A%2F%2Fstatic.wanted.co.kr%2Ffavicon%2F144x144.png&w=60&q=90"
    } 
]